{
    "addons": {
      "{34b514f8-3331-4f3c-9028-f7b743c6e770}": {
        "updates": [
          {
            "version": "0.3",
            "update_link": "https://github.com/lehnenno/BetterScoreSaber/releases/download/v0.3/betterscoresaber-0.3-an+fx.xpi"
          },
          {
            "version": "0.4",
            "update_link": "https://github.com/lehnenno/BetterScoreSaber/releases/download/v0.4/betterscoresaber-0.4-an+fx.xpi"
          },
          {
            "version": "0.5",
            "update_link": "https://github.com/lehnenno/BetterScoreSaber/releases/download/v0.5/betterscoresaber-0.5-an+fx.xpi"
          },
          {
            "version": "0.6",
            "update_link": "https://github.com/lehnenno/BetterScoreSaber/releases/download/v0.6/betterscoresaber-0.6-an+fx.xpi"
          },
          {
            "version": "0.7",
            "update_link": "https://github.com/lehnenno/BetterScoreSaber/releases/download/v0.7/betterscoresaber-0.7-an+fx.xpi"
          },
          {
            "version": "0.8",
            "update_link": "https://github.com/lehnenno/BetterScoreSaber/releases/download/v0.8/betterscoresaber-0.8-an+fx.xpi"
          },
          {
            "version": "0.9",
            "update_link": "https://github.com/lehnenno/BetterScoreSaber/releases/download/v0.9/betterscoresaber-0.9-an+fx.xpi"
          },
          {
            "version": "0.10",
            "update_link": "https://github.com/lehnenno/BetterScoreSaber/releases/download/v0.10/betterscoresaber-0.10-an+fx.xpi"
          },
          {
            "version": "1.1",
            "update_link": "https://github.com/lehnenno/BetterScoreSaber/releases/download/v1.1/betterscoresaber-1.1-an+fx.xpi"
          }
        ]
      }
    }
  }